{
  "schemaVersion": "tiangong.i18n-locale-activation.v1",
  "locale": "fr-FR",
  "source": {
    "baselineSha": "c26f306e82ac66f50a56aafe8f89ea96c0b0c67d",
    "sourceManifestDigest": "4f5dc2600ec7150246cf76b5f338a41a6bf1e2943327f639aaf3ef00a4414391"
  },
  "registry": {
    "canonicalLocale": "fr-FR",
    "aliases": ["fr", "fr-*", "fr_*", "fr_*.UTF-8", "fr_*.UTF-8@*"],
    "direction": "ltr",
    "adapters": { "antDesign": "fr_FR", "dayjs": "fr", "intl": "fr-FR", "report": "fr_FR" },
    "fallbacks": {
      "documentationLocale": "en-US",
      "documentationUrl": "https://docs.tiangong.earth/en",
      "legalLocale": "en-US",
      "dataLanguage": "en",
      "serviceLocale": "en-US"
    },
    "environment": {
      "titleKey": "APP_TITLE_FR_FR",
      "loginSubtitleKey": "APP_LOGIN_SUBTITLE_FR_FR"
    },
    "registryDigest": "b4703b214db281020397fa5714021d7cd912b66bde9c5bd2a55108259ad06bd8"
  },
  "evidence": {
    "contextDigest": "b674147e6e8b1fa4a8ade226eb5e382dea7eed6618c4c37f4e1330278ffd0d8d",
    "qualityDigest": "35c318a99e3a897f96581b4de267b68a51008a22f9f74d9f5ec24cfd7a8d527d",
    "correctionLedgerDigest": "af8bed7cc80fddd36ad049f8ae9a17e4f3f9a960bcc50f31d6df42c169807fb2",
    "routeViewCoverageDigest": "6c3acda5349217420e6f8a018d8cc8df11bff457844dc5620eb43c3b4b1321cf",
    "fallbackContractDigest": "d90c7df3c25816430450a197b7adf1eff7081ae3945c7a8d6932232f3c7b6a75",
    "localeFallbackRowCount": 6
  },
  "ciSafeCommands": {
    "localeAudit": "npm run i18n:locale:audit -- --locale fr-FR",
    "context": "npm run i18n:context:check -- --locale fr-FR",
    "quality": "npm run i18n:locale:quality:check -- --locale fr-FR",
    "corrections": "npm run i18n:corrections:check",
    "activation": "npm run i18n:locale:activation:check -- --locale fr-FR"
  },
  "privateConfirmationDependencies": [],
  "historicalGermanBoundary": "Not applicable; this locale has never used translation confirmation files.",
  "checks": {
    "exactTopology": true,
    "contextComplete": true,
    "automatedQualityPassed": true,
    "correctionOverlayPassed": true,
    "fallbackContractPassed": true,
    "ltrCondition": "single-standard; RTL work not applicable",
    "humanTranslationReviewRequired": false
  },
  "activationDigest": "be35fc40a640d633f3f01678d72bd50be71a919710a92a7af9b3be52df2f265a"
}
